sky130A/HelloWorld/digital/comp32/src/comp32.v
/*
 * A simple 32-bit comparator
 *   
 */

module comp32(
    //`ifdef USE_POWER_PINS
    //    inout vdd,	// 1.8V supply
    //    inout vss,	// Digital ground
    //`endif
    a, b, clk, z);

  input [31:0] a, b;  //define inputs and outputs
  input clk;
  output z;

  reg z;

  always @ (posedge clk)
  begin
     if (a > b)
     	z = 1'b1;
     else 
     	z = 1'b0;
  end
endmodule

sky130A/HelloWorld/digital/comp32/tb/tb_comp32.v
//test bench to detect if A > B

`timescale 1ns / 1ps

module top;

  //inputs are reg for test bench.
  //outputs are wire for test bench.
  reg [31:0] a, b;
  reg clk = 0;
  wire z;

  //display inputs and outputs
  initial
  begin
    $dumpfile(`DUMP_FILE_NAME);
    $dumpvars(0,top);
  end

  //apply input vectors
  initial
  begin
    #0	a = 31'h00000000; b = 31'h00000001; 
    #10	a = 31'h00000003; b = 31'h00000002;
    #10 a = 31'h00000003; b = 31'h0000000B;
    #10	a = 31'h00000007; b = 31'h00000002;

    #10	a = 31'h00000006; b = 31'h00000007; 
    #10	a = 31'h00000003; b = 31'h00000002;
    #10 a = 31'h0000000E; b = 31'h0000000F;
    #10	a = 31'h00000006; b = 31'h00000003;

    #10	a = 31'h00000006; b = 31'h00000007; 
    #10	a = 31'h0000000B; b = 31'h0000000A;
    #10 a = 31'h0000000E; b = 31'h0000000F;
    #10	a = 31'h0000000E; b = 31'h00000007;

    #10	a = 31'h00000008; b = 31'h0000000C; 
    #10	a = 31'h0000000B; b = 31'h0000000A;
    #10 a = 31'h0000000E; b = 31'h0000000F;
    #10	a = 31'h0000000E; b = 31'h00000007;

    #10 	$finish;
  end
  
  always #3 clk = !clk;  	

  //instantiate the module into the test bench
  comp32 inst1 (.clk(clk), .z(z), .a(a), .b(b));
endmodule

sky130A/HelloWorld/digital/comp32/simulations/comp32.vcd
$date
	Tue Apr 30 10:23:40 2024
$end
$version
	Icarus Verilog
$end
$timescale
	1ps
$end
$scope module top $end
$var wire 1 ! z $end
$var reg 32 " a [31:0] $end
$var reg 32 # b [31:0] $end
$var reg 1 $ clk $end
$scope module inst1 $end
$var wire 32 % a [31:0] $end
$var wire 32 & b [31:0] $end
$var wire 1 $ clk $end
$var reg 1 ! z $end
$upscope $end
$upscope $end
$enddefinitions $end
$comment Show the parameter values. $end
$dumpall
$end
#0
$dumpvars
b1 &
b0 %
0$
b1 #
b0 "
x!
$end
#3000
0!
1$
#6000
0$
#9000
1$
#10000
b10 #
b10 &
b11 "
b11 %
#12000
0$
#15000
1!
1$
#18000
0$
#20000
b1011 #
b1011 &
#21000
0!
1$
#24000
0$
#27000
1$
#30000
0$
b10 #
b10 &
b111 "
b111 %
#33000
1!
1$
#36000
0$
#39000
1$
#40000
b111 #
b111 &
b110 "
b110 %
#42000
0$
#45000
0!
1$
#48000
0$
#50000
b10 #
b10 &
b11 "
b11 %
#51000
1!
1$
#54000
0$
#57000
1$
#60000
0$
b1111 #
b1111 &
b1110 "
b1110 %
#63000
0!
1$
#66000
0$
#69000
1$
#70000
b11 #
b11 &
b110 "
b110 %
#72000
0$
#75000
1!
1$
#78000
0$
#80000
b111 #
b111 &
#81000
0!
1$
#84000
0$
#87000
1$
#90000
0$
b1010 #
b1010 &
b1011 "
b1011 %
#93000
1!
1$
#96000
0$
#99000
1$
#100000
b1111 #
b1111 &
b1110 "
b1110 %
#102000
0$
#105000
0!
1$
#108000
0$
#110000
b111 #
b111 &
#111000
1!
1$
#114000
0$
#117000
1$
#120000
0$
b1100 #
b1100 &
b1000 "
b1000 %
#123000
0!
1$
#126000
0$
#129000
1$
#130000
b1010 #
b1010 &
b1011 "
b1011 %
#132000
0$
#135000
1!
1$
#138000
0$
#140000
b1111 #
b1111 &
b1110 "
b1110 %
#141000
0!
1$
#144000
0$
#147000
1$
#150000
0$
b111 #
b111 &
#153000
1!
1$
